tsv2json/__init__.py
tsv2json/bin/__init__.py
tsv2json/bin/main.py
tsv2json/core/__init__.py
tsv2json/version/version.json
tsv2json-1.0.dist-info/METADATA
tsv2json-1.0.dist-info/WHEEL
tsv2json-1.0.dist-info/entry_points.txt
tsv2json-1.0.dist-info/top_level.txt
tsv2json-1.0.dist-info/RECORD
